apos_cli/__init__.py
apos_cli/api.py
apos_cli/apos.py
apos_cli/misc.py
apos_cli-0.1.5.dist-info/entry_points.txt
apos_cli-0.1.5.dist-info/WHEEL
apos_cli-0.1.5.dist-info/METADATA
apos_cli-0.1.5.dist-info/RECORD
